sway_input_config/__init__.py
sway_input_config/main.py
sway_input_config/ui_about.py
sway_input_config/ui_mainwindow.py
sway_input_config/ui_selectlayout.py
sway_input_config/utils.py
sway_input_config/data/defaults.json
sway_input_config/data/kbd_model.json
sway_input_config/data/layouts.json
sway_input_config/data/logo_sic.png
sway_input_config/data/shortcuts.json
sway_input_config/data/variants.json
sway_input_config/langs/lang_be_BY.qm
sway_input_config/langs/lang_be_BY.ts
sway_input_config/langs/lang_ru_RU.qm
sway_input_config/langs/lang_ru_RU.ts
sway_input_config/langs/lang_uk_UA.qm
sway_input_config/langs/lang_uk_UA.ts
sway_input_config/ui/about.ui
sway_input_config/ui/mainwindow.ui
sway_input_config/ui/selectlayout.ui
sway_input_config-1.3.2.data/data/share/applications/sway-input-config.desktop
sway_input_config-1.3.2.data/data/share/icons/hicolor/64x64/apps/sway-input-config.png
sway_input_config-1.3.2.data/data/share/metainfo/io.github.Sunderland93.sway-input-config.appdata.xml
sway_input_config-1.3.2.dist-info/LICENSE
sway_input_config-1.3.2.dist-info/METADATA
sway_input_config-1.3.2.dist-info/WHEEL
sway_input_config-1.3.2.dist-info/entry_points.txt
sway_input_config-1.3.2.dist-info/top_level.txt
sway_input_config-1.3.2.dist-info/RECORD
