Metadata-Version: 2.1
Name: sway-input-config
Version: 1.3.2
Summary: input devices configurator for sway
Home-page: https://github.com/Sunderland93/sway-input-config
Author: Aleksey Samoilov
Author-email: samoilov.lex@gmail.com
License: GPL-3
License-File: LICENSE
Requires-Dist: PySide2
Requires-Dist: i3ipc
